jpfreq/__init__.py
jpfreq/jp_frequency_list.py
jpfreq/kanji.py
jpfreq/main.py
jpfreq/text_info.py
jpfreq/util.py
jpfreq/word.py
jpfreq/word_slot.py
jpfreq/exporters/__init__.py
jpfreq/exporters/iexporter.py
jpfreq/exporters/json.py
jpfreq-0.4.0.dist-info/METADATA
jpfreq-0.4.0.dist-info/WHEEL
jpfreq-0.4.0.dist-info/licenses/LICENSE
jpfreq-0.4.0.dist-info/RECORD
