Metadata-Version: 2.1
Name: JPFreq
Version: 0.4.0
Summary: A Python module which allows for the easy frequency analysis of Japanese text
Project-URL: Homepage, https://github.com/Marley-Mulvin-Broome/JapaneseFrequencyProcessor
Project-URL: Source, https://github.com/Marley-Mulvin-Broome/JapaneseFrequencyProcessor
Project-URL: Documentation, https://marley-mulvin-broome.github.io/JapaneseFrequencyProcessor
Author-email: Marley Mulvin Broome <marley.developer@gmail.com>
Maintainer-email: Marley Mulvin Broome <marley.developer@gmail.com>
License: MIT License
License-File: LICENSE
Keywords: Anime,Frequency,Japanese,Japanese Learning,Japanese Study,Language Learning,Manga,Tool
Classifier: Development Status :: 3 - Alpha
Classifier: Intended Audience :: Developers
Classifier: License :: OSI Approved :: MIT License
Classifier: Natural Language :: Japanese
Classifier: Programming Language :: Python :: 3 :: Only
Classifier: Programming Language :: Python :: 3.10
Classifier: Programming Language :: Python :: 3.11
Classifier: Topic :: Text Processing :: Linguistic
Requires-Python: >=3.10
Requires-Dist: fugashi
Provides-Extra: dev
Requires-Dist: black; extra == 'dev'
Requires-Dist: build; extra == 'dev'
Requires-Dist: fugashi[unidic]; extra == 'dev'
Requires-Dist: pdoc3; extra == 'dev'
Requires-Dist: pytest; extra == 'dev'
Requires-Dist: pytest-cov; extra == 'dev'
Requires-Dist: pytest-xdist; extra == 'dev'
Requires-Dist: ruff; extra == 'dev'
Requires-Dist: twine; extra == 'dev'
